adsorption_file_parser/__init__.py
adsorption_file_parser/_version.py
adsorption_file_parser/bel_common.py
adsorption_file_parser/bel_csv.py
adsorption_file_parser/bel_dat.py
adsorption_file_parser/bel_excel.py
adsorption_file_parser/generic_csv.py
adsorption_file_parser/generic_excel.py
adsorption_file_parser/mic_excel.py
adsorption_file_parser/qnt_txt.py
adsorption_file_parser/sms_dvs_excel.py
adsorption_file_parser/trp_excel.py
adsorption_file_parser/trp_xml.py
adsorption_file_parser/utils/__init__.py
adsorption_file_parser/utils/common_utils.py
adsorption_file_parser/utils/unit_parsing.py
adsorption_file_parser/utils/units.py
adsorption_file_parser-0.3.0.dist-info/LICENSE
adsorption_file_parser-0.3.0.dist-info/METADATA
adsorption_file_parser-0.3.0.dist-info/WHEEL
adsorption_file_parser-0.3.0.dist-info/top_level.txt
adsorption_file_parser-0.3.0.dist-info/zip-safe
adsorption_file_parser-0.3.0.dist-info/RECORD
