Metadata-Version: 2.1
Name: adsorption_file_parser
Version: 0.3.0
Summary: Collection of parsers for (nearly) all commercial adsorption instrumentation
Author-email: AIF Development Team <mail@pauliacomi.com>
License: MIT License
Project-URL: Homepage, https://github.com/AIF-development-team/adsorption-file-parser
Project-URL: Repository, https://github.com/AIF-development-team/adsorption-file-parser.git
Project-URL: Documentation, https://adsorption-file-parser.readthedocs.io
Keywords: adsorption,characterization,porous materials,isotherms,sorption
Classifier: Development Status :: 5 - Production/Stable
Classifier: License :: OSI Approved :: MIT License
Classifier: Operating System :: OS Independent
Classifier: Programming Language :: Python :: 3
Classifier: Programming Language :: Python :: 3 :: Only
Classifier: Intended Audience :: Science/Research
Classifier: Topic :: Scientific/Engineering :: Physics
Classifier: Topic :: Scientific/Engineering :: Chemistry
Requires-Python: >=3.8
License-File: LICENSE
Requires-Dist: python-dateutil
Requires-Dist: xlrd>=1.1
Requires-Dist: xlwt>=1.3
Requires-Dist: openpyxl
Provides-Extra: dev
Requires-Dist: pytest; extra == "dev"
Requires-Dist: pytest-cov; extra == "dev"
Requires-Dist: yapf; extra == "dev"
Requires-Dist: isort; extra == "dev"
Requires-Dist: pylint; extra == "dev"
Requires-Dist: flake8; extra == "dev"
Requires-Dist: flake8-pyproject; extra == "dev"
Requires-Dist: autopep8; extra == "dev"
Requires-Dist: pydocstyle; extra == "dev"
Requires-Dist: pre-commit; extra == "dev"
Provides-Extra: test
Requires-Dist: pytest; extra == "test"
Requires-Dist: pytest-cov; extra == "test"
